dragonfly/__init__.py
dragonfly/__main__.py
dragonfly/_base.py
dragonfly/building.py
dragonfly/colorobj.py
dragonfly/config.py
dragonfly/context.py
dragonfly/dictutil.py
dragonfly/extensionutil.py
dragonfly/model.py
dragonfly/projection.py
dragonfly/properties.py
dragonfly/roof.py
dragonfly/room2d.py
dragonfly/shadingparameter.py
dragonfly/skylightparameter.py
dragonfly/story.py
dragonfly/subdivide.py
dragonfly/windowparameter.py
dragonfly/cli/__init__.py
dragonfly/cli/create.py
dragonfly/cli/edit.py
dragonfly/cli/translate.py
dragonfly/cli/validate.py
dragonfly/writer/__init__.py
dragonfly/writer/building.py
dragonfly/writer/context.py
dragonfly/writer/model.py
dragonfly/writer/room2d.py
dragonfly/writer/story.py
dragonfly_core-1.74.29.dist-info/licenses/LICENSE
dragonfly_core-1.74.29.dist-info/METADATA
dragonfly_core-1.74.29.dist-info/WHEEL
dragonfly_core-1.74.29.dist-info/entry_points.txt
dragonfly_core-1.74.29.dist-info/top_level.txt
dragonfly_core-1.74.29.dist-info/RECORD
